README
setup.py
wither/__init__.py
wither.egg-info/PKG-INFO
wither.egg-info/SOURCES.txt
wither.egg-info/dependency_links.txt
wither.egg-info/requires.txt
wither.egg-info/top_level.txt
wither.egg-info/zip-safe