Metadata-Version: 1.0
Name: wither
Version: 1.1
Summary: XML Generation DSL
Home-page: http://code.pocketnix.org/wither
Author: Da_Blitz
Author-email: code@pocketnix.org
License: MIT BSD
Keywords: XML HTML Generation DSL
Platform: UNKNOWN
